{
"id": 3286,
"authors": [
{"name": "Andy Hall", "email": "ahall@wisconsinwatch.org", "affiliation": "Wisconsin Center for Investigative Journalism"},
{"name": "David Kay Johnston", "email": "davidcay@mac.com", "affiliation": null},
{"name": "Norberto Santana", "email": "nsmaximo8@gmail.com", "affiliation": null}
],
"conference": "IRE",
"year": 2009,
"title": "Back to basics: Finding stories in what is readily available but rarely examined",
"description": "Investigative stories can come from easily accessible information. This tipsheet provides ideas for uncovering issues with minimal resources and time.",
"keywords": ["investigative journalism", "public records", "data analysis", "local government", "trends"]
}
