{
"id": 3345,
"authors": [
{"name": null, "email": null, "affiliation": "Microsoft"},
{"name": "Anthony DeBarros", "email": null, "affiliation": null}
],
"conference": "IRE",
"year": 2010,
"title": "Five Essential Queries for SQL Server",
"description": "Tips on creating temporary tables, updating fields with CASE expressions, joining tables using aliases, ranking query results, and concatenating row values in SQL Server.",
"keywords": ["SQL", "Queries", "Temp Tables", "Joining Tables", "Ranking"]
}
