{
"id": 3396,
"authors": [
{"name": "Ted Mellnik", "email": null, "affiliation": "The Charlotte Observer"},
{"name": "Jaimi Dowdell", "email": null, "affiliation": "IRE/NICAR"}
],
"conference": "Not Listed",
"year": 2010,
"title": "Mining the Web for data and stories",
"description": "Tipsheet on where to find searchable and downloadable data online, including government databases and advanced search strategies. Also covers tips on exploring map services for data extraction.",
"keywords": ["data mining", "online databases", "advanced search", "data extraction", "map services"]
}
