{
"id": 3550,
"authors": [
{"name": "Holly Hacker", "email": "hhacker@dallasnews.com", "affiliation": "Dallas Morning News"},
{"name": "Erica Perez", "email": "eperez@californiawatch.org", "affiliation": "California Watch"},
{"name": "Ben Protess", "email": "ben.protess@nytimes.com", "affiliation": "New York Times"}
],
"conference": "IRE",
"year": 2011,
"title": "Higher Ed: Following the money on campus",
"description": "Tips on investigating financial aspects of higher education institutions, including research grants, vendor records, and student financial aid. Includes resources for tracking university revenues, lobbying data, and public records.",
"keywords": ["university finances", "research grants", "student financial aid", "public records", "higher education"]
}
