{
"id": 3703,
"authors": [
{"name": "Alison Young", "email": "ayoung@usatoday.com", "affiliation": "USA TODAY"}
],
"conference": "Not Listed",
"year": "Not Listed",
"title": "Using Archives and Historical Records for Environmental and Land Use Investigations",
"description": "Tips for utilizing historical records and maps for environmental and land use investigations, including resources like Sanborn maps, city atlases, and industry directories.",
"keywords": ["archives", "historical records", "environmental investigations", "land use", "Sanborn maps"]
}
