{
"id": 4694,
"authors": [
{"name": "Robert Maguire",
"email": "robert@crp.org",
"affiliation": "Center for Responsive Politics"}
],
"conference": "Not Listed",
"year": "Not Listed",
"title": "Turning a Dark Money ¯\_(ツ)_/¯ into Dark Money (⌐■_■)",
"description": "A guide to conducting research on dark money organizations, including tips on finding addresses, linking stakeholders, and utilizing online resources.",
"keywords": ["dark money", "research", "investigation", "data analysis", "IRS"]
}
