{
"id": 4816,
"authors": [
{"name": "Ben Poston",
 "email": "ben.poston@latimes.com",
 "affiliation": "Los Angeles Times"}
],
"conference": "Not Listed",
"year": "Not Listed",
"title": "Flawed UCR data in Los Angeles and Milwaukee",
"description": "Investigative study highlighting misclassification of aggravated assault crimes in Los Angeles and Milwaukee police departments, leading to inaccurate crime reporting.",
"keywords": ["UCR data", "misclassification", "crime reporting", "police departments", "investigative study"]
}
