{
"id": 4904,
"authors": [
{"name": null, "email": null, "affiliation": "http://www.siicex.gob.mx/portalSiicex/Transparencia/Avisos%20Automaticos/avisos-infespecifica.htm"},
{"name": null, "email": null, "affiliation": "http://www.primuslabs.com/psr/platino.aspx"},
{"name": null, "email": null, "affiliation": "http://www.cdpr.ca.gov/docs/enforce/residue/rsmonmnu.htm"}
],
"conference": "Not Listed",
"year": "Not Listed",
"title": "Reporte de Cadena de Suministro de Productos Agricolas de Mexico",
"description": "Sources for finding data on Mexican agricultural exports, food safety inspections, and pesticide residue monitoring in California, along with tips on where to gather information in Mexico and the United States.",
"keywords": ["Export Data", "Food Safety Inspections", "Pesticide Residue Monitoring", "Agricultural Supply Chain", "Mexico"]}
