{
"id": 5115,
"authors": [
{"name": null, "email": null, "affiliation": "OSU School of Media & Strategic Communications"},
{"name": "Joey Senat", "email": "joey.senat@okstate.edu", "affiliation": "OSU School of Media & Strategic Communications"}
],
"conference": "Not Listed",
"year": "Not Listed",
"title": "Navigating the Oklahoma Open Records Act",
"description": "Summary of the Oklahoma Open Records Act, including rights of access, exemptions, making requests, and potential legal actions for denial.",
"keywords": ["open records", "government transparency", "public access", "legal actions"]
}
