{
"id": "5468_2",
"authors": [
{"name": "Nick Penzenstadler", "email": null, "affiliation": null},
{"name": "Kim Smith", "email": null, "affiliation": "Urban Labs, University of Chicago"},
{"name": "Matt Drange", "email": null, "affiliation": null}
],
"conference": "NICAR",
"year": "Not Listed",
"title": "Using Data and Documents to Report on Guns",
"description": "Tips on gathering data and documents for reporting on guns, including common pitfalls and tips on finding reliable sources",
"keywords": ["firearm violence", "regulatory agencies", "trace data", "gun industry"]
}
