{
"id": 5645,
"authors": [
{"name": "Emily Le Coz", "email": null, "affiliation": null},
{"name": "Nate Morabito", "email": null, "affiliation": null},
{"name": "Evan Wyloge", "email": null, "affiliation": null}
],
"conference": "IRE",
"year": 2018,
"title": "HOW TO DO BIG PROJECTS IN A SMALL(ER) NEWSROOM",
"description": "Tips on thinking like an entrepreneur, spreading project tentacles, utilizing easy tools, thinking bigger, turning content, being efficient, asking for help, looking for the right fit, and delivering when working on big investigative projects in a small newsroom.",
"keywords": ["investigative reporting", "small newsroom", "journalism", "data tools", "efficient workflow"]
}
