{
"id": 5830,
"authors": [
{"name": "Tyson Weister", "email": "tyson.weister@census.gov", "affiliation": "U.S. Census Bureau"},
{"name": null, "email": null, "affiliation": "U.S. Census Bureau"},
{"name": "Ron Campbell", "email": null, "affiliation": "Not Listed"},
{"name": "Angeliki Kastanis", "email": null, "affiliation": "Not Listed"}
],
"conference": "NICAR",
"year": 2019,
"title": "Life After FactFinder: The Future of data.census.gov",
"description": "Presentation on the transition from American FactFinder to data.census.gov, highlighting the benefits and improvements of the new platform. Includes a preview of upcoming releases and encourages user feedback.",
"keywords": ["data.census.gov", "Census Bureau", "data dissemination", "user feedback", "data access"]
}
