{
"id": 5865,
"authors": [
{"name": "Miranda S. Spivack", "email": "mirandaspivack@yahoo.com", "affiliation": "Reveal/CIR"},
{"name": "Amy Pyle", "email": null, "affiliation": "Reveal/CIR"},
{"name": "Vickie Baranetsky", "email": null, "affiliation": "Reveal/CIR"}
],
"conference": "IRE",
"year": "Not Listed",
"title": "Open Records Tip Sheet",
"description": "Guide to obtaining public records efficiently through open records requests, with tips on engaging with record keepers, filing requests, and appealing rejections.",
"keywords": ["Public Records", "FOIA", "Journalism", "Transparency", "Government"]
}
