{
"id": 5875,
"authors": [
{"name": "Jenn Topper", "email": "jtopper@rcfp.org", "affiliation": "RCFP"},
{"name": "Katie Townsend", "email": "ktownsend@rcfp.org", "affiliation": "RCFP"},
{"name": "Adam Marshall", "email": "amarshall@rcfp.org", "affiliation": "RCFP"}
],
"conference": "IRE",
"year": "Not Listed",
"title": "Free Legal Resources for Journalists at IRE Conference",
"description": "Provides information on free legal support and resources for journalists and media lawyers to advance First Amendment freedoms. Includes details on upcoming panels and master classes at the IRE conference.",
"keywords": ["First Amendment", "legal support", "journalists", "media law", "IRE"]
}
