{
  "id": "T1729",
  "authors": [
    {
      "name": null,
      "email": null,
      "affiliation": "University of Maryland\u2019s journalism department"
    },
    {
      "name": "Christopher Callahan",
      "email": null,
      "affiliation": "Boston Globe"
    }
  ],
  "conference": "IRE",
  "year": "Not Listed",
  "title": "A Journalist’s Guide to the Internet",
  "description": "Tips and resources for journalists to effectively use the Internet for beat development and data research.",
  "keywords": ["resource", "tips", "journalism", "Internet", "research"]
}
