{
"id": "T1868",
"authors": [
    {
        "name": null,
        "email": null,
        "affiliation": "Investigative Reporters and Editors"
    }
],
"conference": "IRE",
"year": "Not Listed",
"title": "Covering Law and Order: It's a Lifestyle - Five Tips for Covering Law Enforcement, the Courts and Justice Department",
"description": "Tips for journalists on how to effectively cover law enforcement, courts, and the Justice Department, including thinking ahead, utilizing alternate sources, understanding the rules, building relationships with sources, and looking beyond just court processes.",
"keywords": ["investigative reporting", "law enforcement", "courts", "justice department", "sources"]
}
