{
  "id": "6068",
  "authors": [
    {
      "name": "Samantha Sunne",
      "email": null,
      "affiliation": null
    }
  ],
  "conference": "IRE",
  "year": "Not Listed",
  "title": "Scraping Without Programming",
  "description": "This tipsheet covers the basics of web scraping for journalists, including how to extract data from websites using HTML and formulas like ImportHTML and ImportXML. It also introduces point-and-click apps like OutWit Hub and ParseHub.",
  "keywords": [
    "web scraping",
    "HTML",
    "ImportHTML",
    "ImportXML",
    "data extraction"
  ]
}
