{
  "id": "3070",
  "authors": [
    {
      "name": null,
      "email": "ufriverat@gmail.com",
      "affiliation": "St. Petersburg Times"
    }
  ],
  "conference": "NICAR",
  "year": "2008",
  "title": "Web sites and search techniques for reporters",
  "description": "This presentation provides tips and resources for reporters on how to use websites and search techniques to find information. It covers topics such as Google advanced search, telephone directories, and public records.",
  "keywords": [
    "Google",
    "search techniques",
    "public records",
    "telephone directories",
    "newspaper archives"
  ]
}
