{
  "id": "3791",
  "authors": [
    {
      "name": "Ben Poston",
      "email": "bposton@jrn.com",
      "affiliation": "Milwaukee Journal Sentinel"
    },
    {
      "name": "Jennifer LaFleur",
      "email": "jennifer.lafleur@propublica.org",
      "affiliation": "ProPublica"
    },
    {
      "name": "Sam Sommers",
      "email": "Sam.Sommers@tufts.edu",
      "affiliation": "Tufts University"
    },
    {
      "name": "Sandy Close",
      "email": "sclose@newamericamedia.org",
      "affiliation": "New America Media"
    }
  ],
  "conference": "IRE",
  "year": "2012",
  "title": "Investigating Racial Disparities",
  "description": "This tipsheet discusses how to investigate racial disparities in various areas, including city services and traffic stops. It provides guidance on data analysis and methodology.",
  "keywords": [
    "Racial Disparities",
    "Data Analysis",
    "Investigative Reporting",
    "City Services",
    "Traffic Stops"
  ]
}
