{
  "id": "3887",
  "authors": [
    {
      "name": null,
      "email": null,
      "affiliation": "IRE"
    },
    {
      "name": "Joe Germuska",
      "email": null,
      "affiliation": null
    },
    {
      "name": "John Keefe",
      "email": null,
      "affiliation": null
    },
    {
      "name": "Ryan Pitts",
      "email": null,
      "affiliation": null
    },
    {
      "name": "Ian Dees",
      "email": null,
      "affiliation": null
    },
    {
      "name": "Sara Schnadt",
      "email": null,
      "affiliation": null
    },
    {
      "name": "Mark Horvit",
      "email": null,
      "affiliation": "IRE"
    },
    {
      "name": "Heather Henry",
      "email": null,
      "affiliation": "IRE"
    },
    {
      "name": "John Greene",
      "email": null,
      "affiliation": "IRE"
    }
  ],
  "conference": "IRE",
  "year": "Not Listed",
  "title": "Introducing Census Reporter",
  "description": "Census Reporter is a tool designed to make US Census data easy for journalists to use. It provides features such as profile pages, historical data, and visualization tools to help journalists tell stories with census data.",
  "keywords": [
    "US Census",
    "data journalism",
    "census data"
  ]
}
