{"id": "3963", "authors": [{"name": "Jennifer S. Forsyth", "email": null, "affiliation": "The Wall Street Journal"}], "conference": "IRE", "year": "2013", "title": "Writing the Investigative Story", "description": "This tipsheet provides insights from judges on what makes a good investigative story, including originality, importance, and clarity. It also offers suggestions for improvement, such as avoiding overly long stories and using strong graphics.", "keywords": ["investigative reporting", "storytelling", "journalism", "editing", "data journalism"]}
