{
  "id": "3988",
  "authors": [
    {
      "name": "Kelly Carr",
      "email": "Kelly.Carr@BusinessJournalism.org",
      "affiliation": "Reynolds Center for Business Journalism"
    }
  ],
  "conference": "IRE",
  "year": "2013",
  "title": "Shell Companies and Fraud: An Investigative Primer",
  "description": "This tipsheet provides an introduction to shell companies, their legitimate uses, and how they can be used for fraudulent activities such as money laundering and tax evasion. It also offers tools and resources for journalists to investigate shell companies.",
  "keywords": [
    "shell companies",
    "fraud",
    "money laundering",
    "tax evasion",
    "investigative reporting"
  ]
}
