{"id": "4076", 
"authors": [{"name": "Peter Aldhous", "email": "peter@peteraldhous.com", "affiliation": null}], 
"conference": "NICAR", 
"year": "2014", 
"title": "NodeXL for Network analysis", 
"description": "This tipsheet provides a hands-on guide to using NodeXL, a template for Microsoft Excel, to run network analyses and visualize connections between entities. It covers the basics of entering data, filtering, and customizing network visualizations.", 
"keywords": ["network analysis", "NodeXL", "Microsoft Excel", "data visualization", "social media networks"]}
