{
  "id": "4176",
  "authors": [
    {
      "name": null,
      "email": "info@documentcloud.org",
      "affiliation": "DocumentCloud"
    },
    {
      "name": "Jaimi Dowdell",
      "email": null,
      "affiliation": "IRE/NICAR"
    }
  ],
  "conference": "IRE",
  "year": "Not Listed",
  "title": "Using DocumentCloud",
  "description": "This tipsheet provides a guide for reporters on how to use DocumentCloud, a free online tool for managing and collaborating on document sets. It covers the basics of getting started, uploading documents, and using various features such as notes and analysis tools.",
  "keywords": [
    "DocumentCloud",
    "reporting",
    "collaboration",
    "document management",
    "investigative journalism"
  ]
}
