{
  "id": "4220",
  "authors": [
    {
      "name": "Jennifer Levitz",
      "email": null,
      "affiliation": "Wall Street Journal"
    }
  ],
  "conference": "IRE",
  "year": "Not Listed",
  "title": "This Won’t Hurt a Bit: Tips for researching origins of a medical device",
  "description": "The presentation discusses tips for investigating the origins of a medical device, using the example of a procedure called morcellation. It highlights the importance of checking patent filings and talking to trainers to understand the potential risks of the procedure.",
  "keywords": [
    "medical devices",
    "morcellation",
    "patient safety",
    "investigative reporting",
    "healthcare"
  ]
}
