{
    "id": "4279",
    "authors": [
        {
            "name": null,
            "email": null,
            "affiliation": "The Times-Picayune"
        }
    ],
    "conference": "IRE",
    "year": "Not Listed",
    "title": "Watchdogging local government: Contracting and professional services",
    "description": "This tipsheet provides guidance on investigating local government contracting and professional services, including how to find information and what to look for. It covers topics such as public bid laws, campaign contributions, and subcontracts.",
    "keywords": [
        "contracting",
        "professional services",
        "local government",
        "investigative reporting",
        "public records"
    ]
}
