{
  "id": "4477",
  "authors": [
    {
      "name": null,
      "email": null,
      "affiliation": null
    }
  ],
  "conference": "IRE",
  "year": "Not Listed",
  "title": "OFF THE RECORD AGREEMENT",
  "description": "This tipsheet provides guidance for reporters on handling confidential sources and negotiating off-the-record agreements. It outlines key points to clarify and negotiate with sources, including verification of information and protection of identity.",
  "keywords": [
    "off-the-record",
    "confidential sources",
    "journalism ethics",
    "source protection",
    "investigative reporting"
  ]
}
