{
  "id": "4630",
  "authors": [
    {
      "name": null,
      "email": "ccanipe@gmail.com",
      "affiliation": "The Wall Street Journal"
    },
    {
      "name": null,
      "email": "jon.r.mcclure@gmail.com",
      "affiliation": "Dallas Morning News"
    }
  ],
  "conference": "NICAR",
  "year": "2016",
  "title": "Intro to D3 with a simple Scatterplot!",
  "description": "This session covered the basics of creating a scatterplot using D3, including defining scales and axes, and drawing SVG elements. The instructors provided examples and resources for further learning.",
  "keywords": [
    "D3",
    "scatterplot",
    "SVG",
    "data visualization",
    "javascript"
  ]
}
