{
  "id": "4914",
  "authors": [
    {
      "name": "Michael Hudson",
      "email": "mhudson@icij.org",
      "affiliation": "International Consortium of Investigative Journalists"
    },
    {
      "name": null,
      "email": null,
      "affiliation": "Reuters"
    },
    {
      "name": null,
      "email": null,
      "affiliation": "The New York Times"
    }
  ],
  "conference": "IRE",
  "year": "Not Listed",
  "title": "Investigating Offshore Schemes",
  "description": "This tipsheet provides information on how to investigate offshore schemes and understand the complex world of companies, trusts, and foundations. It explains key terms such as layering, beneficial owner, and nominee directors.",
  "keywords": [
    "offshore schemes",
    "investigative reporting",
    "financial secrecy",
    "layering",
    "beneficial owner"
  ]
}
