{
  "id": "5157",
  "authors": [
    {
      "name": "Reena Cruz",
      "email": null,
      "affiliation": "Cometdocs.com"
    }
  ],
  "conference": "IRE",
  "year": "Not Listed",
  "title": "Converting, Storing, and Sharing PDF Documents Online",
  "description": "This tipsheet discusses the challenges of working with PDF documents and provides solutions for converting, storing, and sharing them online. It highlights the features and best practices of using Cometdocs.com for these tasks.",
  "keywords": [
    "PDF conversion",
    "data extraction",
    "document storage",
    "online tools",
    "productivity"
  ]
}
