{
  "id": "5186",
  "authors": [
    {
      "name": "Vicky Nguyen",
      "email": "vicky@nbcbayarea.com",
      "affiliation": "NBC Bay Area"
    }
  ],
  "conference": "National Conference",
  "year": "2017",
  "title": "Digging with Documents",
  "description": "This tipsheet discusses how to use various documents and media, including videos and social media, to investigate stories and hold the powerful accountable. It also provides a list of favorite broadcast documents, such as emails and search warrants.",
  "keywords": [
    "investigative reporting",
    "documents",
    "video",
    "social media",
    "accountability"
  ]
}
