{
  "id": "5203",
  "authors": [
    {
      "name": "Ashley Luthern",
      "email": null,
      "affiliation": "Milwaukee Journal Sentinel"
    }
  ],
  "conference": "IRE",
  "year": "Not Listed",
  "title": "Gaining trust and building rapport: Interviewing victims of violent crime",
  "description": "This tipsheet provides guidance on how to interview victims of violent crime, including being patient, genuine, and honest, as well as using public records to gather information. It also highlights the importance of taking care of oneself when reporting on traumatic events.",
  "keywords": [
    "interviewing victims",
    "violent crime",
    "public records",
    "trauma reporting",
    "investigative journalism"
  ]
}
