{"id": "5228", 
"authors": [
{"name": "Nate Morabito", "email": "nmorabito@wjhl.com", "affiliation": "WJHL-TV"}, 
{"name": "Susan Richardson", "email": "srichardson@chicagoreporter.com", "affiliation": "The Chicago Reporter"}, 
{"name": "Rose Ciotta", "email": "rciotta@edsource.org", "affiliation": "EdSource"}, 
{"name": "Thomas Peele", "email": "tpeele@bayareanewsgroup.com", "affiliation": "Mercury News and East Bay Times"}
], 
"conference": "IRE", 
"year": "Not Listed", 
"title": "Smart strategies for small newsrooms", 
"description": "This tipsheet provides strategies for small newsrooms to produce high-quality investigative reporting, including looking outside the box for help and collaborations, seeking extra funding, and planning investigations effectively. It also emphasizes the importance of being efficient, asking for help, and creating an investigative culture in the newsroom.", 
"keywords": ["investigative reporting", "small newsrooms", "collaboration", "funding", "efficiency"]}
