{
  "id": "5280",
  "authors": [
    {
      "name": "Sarah Hutchins",
      "email": null,
      "affiliation": "IRE & NICAR"
    },
    {
      "name": "Lauren Grandestaff",
      "email": "lauren@ire.org",
      "affiliation": "IRE"
    }
  ],
  "conference": "IRE & NICAR",
  "year": "Not Listed",
  "title": "Backgrounding tips from a journalist and librarian",
  "description": "This tipsheet provides techniques for backgrounding people and businesses, including using search engines, public records, and databases. It also offers advice on how to verify information and organize research.",
  "keywords": [
    "backgrounding",
    "investigative reporting",
    "public records",
    "research techniques"
  ]
}
