{"id": "5307", 
"authors": [{"name": "Cheryl W. Thompson", "email": "cheryl.thompson@washpost.com", "affiliation": "The Washington Post"}], 
"conference": "IRE", 
"year": "2017", 
"title": "Investigating Police Use of Force and Gun-Related Crimes", 
"description": "This tipsheet discusses how to investigate police use of force, including Taser-related deaths, and gun-related crimes using data and public records. It provides guidance on where to find data and how to analyze it.", 
"keywords": ["police use of force", "Taser deaths", "gun violence", "investigative reporting", "data analysis"]}
