{
  "id": "5348",
  "authors": [
    {
      "name": "Matt Clark",
      "email": "matt.clark@newsday.com",
      "affiliation": "Newsday"
    }
  ],
  "conference": "IRE",
  "year": "Not Listed",
  "title": "Uncovering Inequity in Property Taxes",
  "description": "This tipsheet explores how property taxes can be unfair and unequal, using a fictional example to illustrate the problems. It discusses how wealthy individuals can exploit loopholes to reduce their tax bills, while others may struggle to pay.",
  "keywords": [
    "property taxes",
    "inequity",
    "tax exemptions",
    "assessments"
  ]
}
