{
  "id": "5352",
  "authors": [
    {
      "name": "Martin Shelton",
      "email": null,
      "affiliation": null
    }
  ],
  "conference": "IRE",
  "year": "Not Listed",
  "title": "Beyond Signal: Secure messaging channels & confidential tip pages",
  "description": "This tipsheet discusses ways to securely collect information and protect sources, including the use of encryption and secure messaging channels. It covers various methods for keeping conversations private and sources safe.",
  "keywords": [
    "secure messaging",
    "encryption",
    "source protection",
    "Signal",
    "SecureDrop"
  ]
}
