{
"id": "5462",
"authors": [
{"name": "Dylan Purcell", "email": "dpurcell@phillynews.com", "affiliation": "The Philadelphia Inquirer & Daily News"}
],
"conference": "NICAR",
"year": "2018",
"title": "Uncovering environmental hazards faced by urban children",
"description": "This tipsheet discusses how to investigate environmental hazards such as lead paint, asbestos, and mold that affect urban children. It provides resources and methods for testing and researching these issues.",
"keywords": ["lead paint", "asbestos", "mold", "environmental hazards", "urban health"]
}
