{
  "id": "5517",
  "authors": [
    {
      "name": "Cheryl W. Thompson",
      "email": "Cheryl.Thompson@washpost.com",
      "affiliation": "The Washington Post"
    }
  ],
  "conference": "IRE",
  "year": "2018",
  "title": "The Investigative Interview",
  "description": "This tipsheet provides guidance on conducting effective investigative interviews, including preparation, persistence, and strategy. It also includes an example of a letter to a potential interview subject.",
  "keywords": [
    "investigative interviewing",
    "interview techniques",
    "journalism"
  ]
}
