{
  "id": "5610_presentation",
  "authors": [
    {
      "name": "Maria Perez",
      "email": "maria.perez@jrn.com",
      "affiliation": "Milwaukee Journal Sentinel"
    }
  ],
  "conference": "IRE",
  "year": "Not Listed",
  "title": "Developing sources on the beat",
  "description": "This presentation provides tips and strategies for developing sources as a journalist, including meeting people in person and thinking outside the box to find diverse sources. It also offers advice on how to find sources when it seems like there are none.",
  "keywords": [
    "source development",
    "journalism tips",
    "investigative reporting",
    "beat reporting",
    "source building"
  ]
}
