{
  "id": "5625",
  "authors": [
    {
      "name": "Leslie Postal",
      "email": null,
      "affiliation": "Orlando Sentinel"
    },
    {
      "name": "Beth Kassab",
      "email": null,
      "affiliation": "Orlando Sentinel"
    },
    {
      "name": "Annie Martin",
      "email": null,
      "affiliation": "Orlando Sentinel"
    }
  ],
  "conference": "IRE",
  "year": "Not Listed",
  "title": "Schools Without Rules",
  "description": "The Orlando Sentinel investigated private schools that take Florida school scholarships or vouchers, revealing issues with these schools. The investigation involved visiting schools and requesting documents to uncover problems.",
  "keywords": [
    "private schools",
    "vouchers",
    "investigative reporting",
    "education",
    "Florida"
  ]
}
