{"id": "5683_2", "authors": [{"name": "Brian Freskos", "email": "bfreskos@thetrace.org", "affiliation": "The Trace"}], "conference": "IRE", "year": "Not Listed", "title": "GUN THEFT AND CRIME", "description": "This tipsheet discusses how to investigate gun theft and crime using data, including statistics on stolen guns and methods for tracking them. It also provides resources for finding data on gun-related injuries and deaths.", "keywords": ["gun theft", "crime", "investigative reporting", "data journalism", "firearms"]}
