{
  "id": "5694",
  "authors": [
    {
      "name": null,
      "email": "Thompson.lea@gmail.com",
      "affiliation": null
    }
  ],
  "conference": "IRE",
  "year": "Not Listed",
  "title": "25 Ways to Stop or at Least Delay a Story",
  "description": "This tipsheet describes tactics used by companies to delay or stop investigative stories from being published. It provides a list of 25 ways that companies may try to prevent stories from being told.",
  "keywords": [
    "investigative reporting",
    "story delay tactics",
    "media intimidation"
  ]
}
