{
  "id": "5725",
  "authors": [
    {
      "name": "Jonathan D. Salant",
      "email": null,
      "affiliation": "NJ Advance Media"
    }
  ],
  "conference": "IRE",
  "year": "Not Listed",
  "title": "Getting the goods on members of Congress without a D.C. bureau",
  "description": "This tipsheet provides information on how to investigate members of Congress without being in Washington D.C., including using financial disclosure forms and interest group ratings. It also suggests ways to find sources who know about your lawmaker.",
  "keywords": [
    "Congress",
    "financial disclosure",
    "interest groups",
    "investigative reporting"
  ]
}
