{
  "id": "5738",
  "authors": [
    {
      "name": null,
      "email": null,
      "affiliation": null
    }
  ],
  "conference": "IRE",
  "year": "Not Listed",
  "title": "Family life and investigative journalism",
  "description": "This tipsheet provides advice on balancing family life with the demands of investigative journalism, including managing guilt, creating a supportive work environment, and prioritizing family time. It offers practical tips for parents working in investigative journalism.",
  "keywords": [
    "work-life balance",
    "investigative journalism",
    "parenting",
    "flexible hours",
    "supportive workplace"
  ]
}
