{
  "id": "5812",
  "authors": [
    {
      "name": "Anupama Narayanswamy",
      "email": null,
      "affiliation": "Washington Post"
    },
    {
      "name": "Sandra Fish",
      "email": null,
      "affiliation": null
    },
    {
      "name": "AmyJo Brown",
      "email": null,
      "affiliation": null
    }
  ],
  "conference": "IRE",
  "year": "Not Listed",
  "title": "Breaking out of the traditional election-cycle narrative",
  "description": "This tipsheet provides ideas and resources for reporting on campaign finance data outside of the traditional election cycle. It includes examples of stories and datasets that can be used to investigate campaign finance and lobbying at the federal, state, and local levels.",
  "keywords": [
    "campaign finance",
    "lobbying",
    "election cycle",
    "data journalism",
    "investigative reporting"
  ]
}
