{
  "id": "herzog_mappingthenews",
  "authors": [
    {
      "name": "David Herzog",
      "email": "herzogd@missouri.edu",
      "affiliation": "Missouri School of Journalism"
    }
  ],
  "conference": "NICAR",
  "year": "2012",
  "title": "Mapping the news",
  "description": "This tipsheet discusses the use of geographic information systems (GIS) in data journalism to uncover new knowledge and create interactive maps. It covers the basics of GIS, including geocoding, layering, and spatial analysis.",
  "keywords": [
    "GIS",
    "data journalism",
    "mapping",
    "geographic information systems",
    "spatial analysis"
  ]
}
