{
  "id": "T1532",
  "authors": [
    {
      "name": "Jean Packard",
      "email": "jean.packard@baltsun.com",
      "affiliation": "Baltimore Sun"
    }
  ],
  "conference": "NICAR",
  "year": "2002",
  "title": "Fee Services for Information for Backgrounding",
  "description": "This tipsheet provides information on fee-based services for background research, including company names, costs, and features. It helps journalists find the best resources for their investigative work.",
  "keywords": [
    "background research",
    "fee-based services",
    "investigative reporting"
  ]
}
