{
  "id": "T1815",
  "authors": [
    {
      "name": null,
      "email": "matte@nytimes.com",
      "affiliation": "The New York Times"
    }
  ],
  "conference": "NICAR",
  "year": "Not Listed",
  "title": "Stored Procedures and Cursors with SQL Server",
  "description": "This tipsheet provides examples of how to calculate medians, ranks, percentiles, quintiles, and crosstabs in Microsoft SQL Server. It includes stored procedures and cursors for hands-on practice.",
  "keywords": [
    "SQL Server",
    "stored procedures",
    "cursors",
    "medians",
    "ranks"
  ]
}
