{
  "id": "T1862",
  "authors": [
    {
      "name": "Thomas Maier",
      "email": "Tmaier@Newsday.com",
      "affiliation": "New York Newsday"
    }
  ],
  "conference": "IRE",
  "year": "2003",
  "title": "Death on the Job ? Danger and Profiteering",
  "description": "This tipsheet discusses ways to document workplace deaths and safety conditions for undocumented immigrant workers in the United States. It provides resources such as government agencies and organizations that track worker fatalities and violations.",
  "keywords": [
    "workplace deaths",
    "undocumented immigrants",
    "worker safety",
    "immigration",
    "investigative reporting"
  ]
}
