{
  "id": "T2046",
  "authors": [
    {
      "name": "Carolyn Edds",
      "email": "carolyn@ire.org",
      "affiliation": "IRE/NICAR"
    }
  ],
  "conference": "NICAR",
  "year": "2004",
  "title": "Finding and Using Government Databases",
  "description": "This tipsheet provides guidance on finding and using government databases for investigative reporting, including searching online and using tools like Google Alerts. It also highlights resources available through IRE and NICAR.",
  "keywords": [
    "government databases",
    "investigative reporting",
    "Google Alerts",
    "data analysis",
    "online research"
  ]
}
