{
  "id": "T2059",
  "authors": [
    {
      "name": null,
      "email": "waite@sptimes.com",
      "affiliation": "SPTimes"
    }
  ],
  "conference": "IRE",
  "year": "Not Listed",
  "title": "Investigative stories using Census data",
  "description": "This tipsheet provides resources and guidance for using US Census data to create investigative stories. It includes links to useful websites and tools, such as the American Factfinder and the Economic Census.",
  "keywords": [
    "Census data",
    "investigative reporting",
    "data journalism",
    "US Census Bureau",
    "American Factfinder"
  ]
}
