{
  "id": "T2349",
  "authors": [
    {
      "name": "Rick Linsk",
      "email": "rlinsk@pioneerpress.com",
      "affiliation": "St. Paul Pioneer Press"
    }
  ],
  "conference": "Hollywood CAR",
  "year": "2005",
  "title": "Examining long-term care with CAR",
  "description": "This tipsheet provides guidance on investigating nursing homes using computer-assisted reporting techniques and various data sources. It highlights the importance of examining state inspection data, complaint records, and death certificates to uncover potential mistreatment of elderly people.",
  "keywords": [
    "nursing homes",
    "long-term care",
    "investigative reporting",
    "computer-assisted reporting",
    "elderly abuse"
  ]
}
