{
  "id": "T2619",
  "authors": [
    {
      "name": "Jaimi Dowdell",
      "email": "jdowdell@post-dispatch.com",
      "affiliation": "St. Louis Post-Dispatch"
    },
    {
      "name": "Aaron Kessler",
      "email": "akessler@vpap.org",
      "affiliation": "Virginia Public Access Project"
    }
  ],
  "conference": "IRE",
  "year": "Not Listed",
  "title": "Social Network Analysis for Stories",
  "description": "This tipsheet introduces social network analysis as a method to research relationships between individuals and organizations, and provides examples of its application in investigative journalism. It also lists resources and software for getting started with social network analysis.",
  "keywords": [
    "social network analysis",
    "investigative journalism",
    "data analysis",
    "relationships",
    "networks"
  ]
}
