{
  "id": "T2627",
  "authors": [
    {
      "name": "Paul D'Ambrosio",
      "email": "pmd@app.com",
      "affiliation": "Asbury Park (NJ) Press"
    },
    {
      "name": "James W. Prado Roberts",
      "email": null,
      "affiliation": "Asbury Park (NJ) Press"
    }
  ],
  "conference": "IRE",
  "year": "Not Listed",
  "title": "Tracking sex offenders: How to find the ones who have dropped off the radar screen",
  "description": "This tipsheet explains how to track down sex offenders who are not listed on public registries due to loopholes in the system. It provides steps for journalists to follow, including using data from inmate databases and Internet registries.",
  "keywords": [
    "sex offenders",
    "Megan's Law",
    "investigative reporting",
    "public records",
    "data analysis"
  ]
}
