{
  "id": "T2636",
  "authors": [
    {
      "name": "M.J. Crowley",
      "email": "moose@starledger.com",
      "affiliation": "The Star-Ledger"
    }
  ],
  "conference": "IRE",
  "year": "2006",
  "title": "Advanced Internet: Google Tricks, Deep Web, and Resurrecting the Dead",
  "description": "This tipsheet provides an overview of advanced Google search techniques and tools for investigative reporters. It covers various search operators, features, and services such as Google Groups, News, Froogle, and Maps.",
  "keywords": [
    "Google search",
    "investigative reporting",
    "online research"
  ]
}
