{
"id": "tipsheet",
"authors": [
{
"name": "Scott Pham",
"email": "spham@cironline.org",
"affiliation": "The Center for Investigative Reporting"
},
{
"name": "Brent Jones",
"affiliation": null
},
{
"name": "Allie Kanik",
"affiliation": null
},
{
"name": "Lindsey Cook",
"affiliation": null
}
],
"conference": "NICAR",
"year": 2016,
"title": "Tipsheet for the Lonely Coder Presentation at NICAR 2016 in Denver",
"description": "This tipsheet provides concrete examples and starting points for becoming a data journalist, including story ideas, easy-to-pick-up tools, and a plan to transition from software-user to coding-journalist.",
"keywords": ["data journalism", "coding", "newsroom tools", "NICAR", "Lonely Coder"]
}
