 {
"id": 6030,
"authors": [
{
"name": "Carrie Levine",
"email": null,
"affiliation": "Center for Public Integrity"
},
{
"name": "Robert Maguire",
"email": "rmaguire@citizensforethics.org",
"affiliation": "CREW"
},
{
"name": "Anna Massoglia",
"email": "anna@crp.org",
"affiliation": "OpenSecrets"
}
],
"conference": "IRE",
"year": 2020,
"title": "Tips for Uncovering Dark Money",
"description": "Exploring resources and public records to track how dark money groups spend money in elections and discover who funds them.",
"keywords": ["dark money", "public records", "IRS Form 990", "lobbyists", "FEC", "OpenSecrets"]
}
