 {
"id": 3391,
"authors": [
{
"name": "Shawn McIntosh",
"email": null,
"affiliation": "The Atlanta Journal-Constitution"
}
],
"conference": "IRE",
"year": 2010,
"title": "Government Waste Initiative Tipsheet",
"description": "A guide for reporters on how to uncover government waste, including best documents and records to obtain, policies and procedures to master, and reporting routines and tactics to follow.",
"keywords": [
"government waste",
"investigative journalism",
"public records",
"audits",
"budgets"
]
}
