 {
"id": 3929,
"authors": [
{
"name": "Barbara Gray",
"email": null,
"affiliation": "CUNY Graduate School of Journalism"
}
],
"conference": "NICAR",
"year": "2013",
"title": "Beyond Google 2013: Advanced Web and Social Media Search for Journalists",
"description": "A list of advanced search techniques and tools for journalists, including filter bubbles, private browsing, LinkedIn and Twitter searching, and scholarly resources.",
"keywords": [
"advanced search",
"web",
"social media",
"journalism",
"tools",
"techniques"
]
}
