 {
"id": 4043,
"authors": [
{
"name": "David Donald",
"email": "ddonald@publicintegrity.org",
"affiliation": "The Center for Public Integrity"
},
{
"name": "Jennifer LaFleur",
"email": "jlafleur@cironline.org",
"affiliation": "Center for Investigative Reporting"
}
],
"conference": "NICAR",
"year": 2014,
"title": "The Data-Driven Story",
"description": "A detailed guide to data-driven story research, data acquisition and analysis, methodology, and pitching.",
"keywords": [
"data journalism",
"data analysis",
"story pitching",
"data acquisition",
"investigative reporting"
]
}
