 {
"id": 4568,
"authors": [
{
"name": "Joe Davis",
"email": null,
"affiliation": "Not Listed"
},
{
"name": "Liz Lucas",
"email": null,
"affiliation": "Not Listed"
}
],
"conference": "NICAR",
"year": 2014,
"title": "Data Reporting on U.S. Infrastructure: Key Sources",
"description": "A guide to finding and using data to report on U.S. infrastructure, presented at NICAR 2014.",
"keywords": [
"data reporting",
"infrastructure",
"NICAR",
"dam safety",
"pipeline safety",
"drinking water systems"
]
}
