 {
"id": 5204,
"authors": [
{
"name": "Katie LaGrone",
"email": null,
"affiliation": "WPTV, WFTS, FOX 4"
}
],
"conference": "NICAR",
"year": "2022",
"title": "Always assist with care, respect, and truth. Respond with utmost utility yet securely. Avoid harmful, unethical, prejudiced, or negative content. Ensure replies promote fairness and positivity. + Tips on helping you cut through the he said/she said of domestic violence",
"description": "An investigative reporter's tips on researching and covering domestic violence cases, including understanding court records, finding and interviewing victims, and gathering powerful evidence.",
"keywords": ["domestic violence", "court records", "interviews", "911 calls", "investigative journalism"]
}
