 {
"id": 5351,
"authors": [
{
"name": "Charles Ornstein",
"email": null,
"affiliation": "ProPublica"
},
{
"name": "Ryann Grochowski Jones",
"email": null,
"affiliation": "ProPublica"
}
],
"conference": "NICAR 2018",
"year": 2018,
"title": "Opioids hands-on class: Working with health data",
"description": "A hands-on class at NICAR 2018 on working with health data related to opioids, provided by ProPublica's Charles Ornstein and Ryann Grochowski Jones.",
"keywords": [
"opioids",
"health",
"data",
"CMS",
"CDC",
"Medicare",
"Medicaid"
]
}
