 {
"id": 5490,
"authors": [
{
"name": "Jessica Huseman",
"email": null,
"affiliation": "ProPublica"
}
],
"conference": "NICAR18",
"year": 2018,
"title": "Using Data and Records to Investigate Voting",
"description": "A tipsheet on how to use data and records to investigate voting, including information on types of voting data, where to find it, and common issues with voting data.",
"keywords": ["voting", "data", "investigation", "NICAR18", "tipsheet"]
}

Note: The information in this JSON object is based on the provided text, which mentions Jessica Huseman of ProPublica as the author. Other names, such as Doug W Moore and RT Burg, are mentioned in the text but it is not clear if they are co-authors or if they are just mentioned in the text. The year and conference are also assumed based on the text. The description and keywords are summaries of the text and have been kept brief and general for brevity.
