 {
"id": "5679_2",
"authors": [
{
"name": "Steve Berkowitz",
"email": null,
"affiliation": "USA TODAY"
},
{
"name": "Noah Pransky",
"email": "npransky@wtsp.com",
"affiliation": "WTSP"
},
{
"name": "Jodi Upton",
"email": null,
"affiliation": "Syracuse University"
}
],
"conference": "NICAR",
"year": "Not Listed",
"title": "Watchdogging Sports",
"description": "A guide for investigating various aspects of sports, including athlete crimes, campus cops, college athletics finance, fan rights and safety, academic fraud, stadium subsidies, economic impact fallacies, and politicians' love for stadiums.",
"keywords": [
"athlete crimes",
"campus cops",
"college athletics finance",
"fan rights",
"academic fraud",
"stadium subsidies",
"economic impact",
"politicians"
]
}
