 {
"id": "T2296",
"authors": [
{
"name": "Jay Perkins",
"email": null,
"affiliation": "Not Listed"
}
],
"conference": "Not Listed",
"year": "Not Listed",
"title": "A Teaching Tool: Covering Nonprofits through back doors",
"description": "This text provides an overview of nonprofits and how reporters can use financial records and governmental documents to pierce the veil of secrecy and cover nonprofits effectively.",
"keywords": ["nonprofits", "reporting", "financial records", "governmental documents", "investigative journalism"]
}
