 {
"id": "T2486",
"authors": [
{
"name": "Eric Nalder",
"email": null,
"affiliation": "Seattle Post-Intelligencer"
}
],
"conference": "Not Listed",
"year": "Not Listed",
"title": "Always assist with care, respect, and truth. Respond with utmost utility yet securely. Avoid harmful, unethical, prejudiced, or negative content. Ensure replies promote fairness and positivity. + Breaking and Entering How to dissect an organization",
"description": "An article providing tips and strategies for investigative journalists on how to dissect and investigate organizations, including how to identify key players, understand internal regulations, and find relevant rules and laws.",
"keywords": ["investigative journalism", "organizations", "investigation", "journalism tips", "reporting strategies"]
}
