 {
"id": "T2732",
"authors": [
{
"name": "Vivienne Walt",
"email": "vivwalt@yahoo.com",
"affiliation": "Time Magazine"
}
],
"conference": "Not Listed",
"year": "Not Listed",
"title": "Tips for Women Journalists Doing International Investigations",
"description": "A list of style-focused tips for women journalists conducting international investigations, with a focus on reporting in Muslim communities.",
"keywords": [
"journalism",
"international reporting",
"style",
"women journalists",
"Muslim communities"
]
}
