 {
"id": "T54",
"authors": [
{
"name": "Ray Carter",
"email": null,
"affiliation": "The Crimson"
}
],
"conference": "Not Listed",
"year": "1994",
"title": "Questions on Police Violence during Arrests",
"description": "This document raises concerns about police violence, highlighting instances of people with mental health issues or objects during arrests.",
"keywords": [
"police violence",
"arrests",
"civil rights", "victims", "accountability"
]
}

This JSON object represents the generated file. The authors' affiliation is based on the name of the news organization mentioned in the text. The keywords are carefully selected from the questions in the prompt, aiming to encompass the main topics being discussed. The conference and year values are based on the provided information in the prompt.
