  {
"id": 2886,
"authors": [
{
"name": "Duff Wilson",
"email": "dwilson@nytimes.com",
"affiliation": "The New York Times"
}
],
"conference": "IRE National Conference",
"year": 2006,
"title": "Consejos básicos para investigaciones deportivas",
"description": "Article discussing techniques for investigating sports stories, with a focus on a specific story about athletes receiving fake diplomas. The story was a finalist for the ASPE National Awards for Best Investigative Reporting in Sports.",
"keywords": [
"sports investigations",
"fake diplomas",
"athletes",
"NCAA",
"Florida"
]
}
