  {
"id": 2939,
"authors": [
{
"name": "Mark Greenblatt",
"email": null,
"affiliation": "KHOU-TV (CBS, Houston)"
},
{
"name": "Keith Tomshe",
"email": null,
"affiliation": "KHOU-TV (CBS, Houston)"
}
],
"conference": "IRE",
"year": 2007,
"title": "Visualizing the Data",
"description": "Tips for effectively communicating data findings to an audience, including the use of visuals, storytelling, and collaboration with graphics departments.",
"keywords": [
"data visualization",
"storytelling",
"graphics",
"communication",
"journalism"
]
}
