  {
"id": 3210,
"authors": [
{
"name": "Steve Doig",
"email": null,
"affiliation": "Investigative Reporters and Editors, Inc."
},
{
"name": "Paul Overberg",
"email": null,
"affiliation": "Investigative Reporters and Editors, Inc."
}
],
"conference": "IRE",
"year": 2009,
"title": "Mining Census Data and Preparing p for 2010",
"description": "Article discussing the American Community Survey and its uses for journalists",
"keywords": [
"American Community Survey",
"Census data",
"journalism",
"data analysis"
]
}
