  {
"id": 3215,
"authors": [
{
"name": "Jennifer LaFleur",
"email": "jlafleur@ire.org",
"affiliation": "Investigative Reporters and Editors, Inc."
},
{
"name": "Robert Hanneman",
"email": "hanneman@ucr.edu",
"affiliation": "University of California, Riverside"
}
],
"conference": "IRE",
"year": "2009",
"title": "The Nuts and Bolts of Social Network Analysis",
"description": "A guide to understanding and analyzing social networks, including resources and software options.",
"keywords": [
"social network analysis",
"Madoff",
"Hank Paulson",
"Austin",
"influence"
]
}
