  {
"id": 3365,
"authors": [
{
"name": "Michael Grabell",
"email": "mgrabell@propublica.org",
"affiliation": "ProPublica"
},
{
"name": "Ben Poston",
"email": "bposton@journalsentinel.com",
"affiliation": "Milwaukee Journal-Sentinel"
}
],
"conference": "Not Listed",
"year": "Not Listed",
"title": "Following the Stimulus Money",
"description": "A guide to resources for investigating the use of stimulus funds, including Recovery.gov, Federal Procurement Data System, and USASpending.gov.",
"keywords": [
"stimulus",
"Recovery.gov",
"procurement",
"spending",
"data"
]
}
