  {
"id": 3502,
"authors": [
{
"name": "Scott Cohn",
"email": "Scott.Cohn@nbcuni.com",
"affiliation": "CNBC"
}
],
"conference": "IRE",
"year": 2011,
"title": "Remington Under Fire: A CNBC Investigation",
"description": "An investigation into the safety of Remington's 700 series bolt-action rifles, which have been linked to numerous deaths and injuries, and the company's knowledge of a design flaw.",
"keywords": [
"Remington",
"700 series",
"bolt-action rifles",
"product safety",
"design flaw"
]
}
