  {
"id": 3511,
"authors": [
{
"name": "David Andreatta",
"email": "dandreat@democratandchronicle.com",
"affiliation": "Rochester Democrat and Chronicle"
},
{
"name": "Orlando IRE Conference",
"email": null,
"affiliation": null
}
],
"conference": "IRE",
"year": "2011",
"title": "Examining Public Authorities and Local Development Corporations",
"description": "Tips for investigating public authorities and local development corporations, including how to Access budgets, annual reports, and meeting minutes, and how to identify potential issues such as waste and abuse.",
"keywords": [
"public authorities",
"local development corporations",
"investigative reporting",
"government accountability",
"transparency"
]
}
