  {
"id": 3708,
"authors": [
{
"name": "Rose Ciotta",
"email": "rciotta@phillynews.com",
"affiliation": "The Philadelphia Inquirer"
},
{
"name": "Anthony DeBarros",
"email": "adebarros@usatoday.com",
"affiliation": "USA TODAY"
},
{
"name": "Sarah Moughty",
"email": "sarah_moughty@wgbh.org",
"affiliation": "Frontline"
}
],
"conference": "IRE",
"year": "2012",
"title": "Managing Multimedia Projects",
"description": "A discussion on managing multimedia projects, including finding the right idea, elements, and people, keeping the project on track, and maintaining momentum.",
"keywords": ["multimedia", "project management", "journalism", "IRE", "2012"]
}
