  {
"id": 4626,
"authors": [
{
"name": "Philip Meyer",
"email": null,
"affiliation": "University of North Carolina"
},
{
"name": "Shawn McIntosh",
"email": null,
"affiliation": "USA TODAY"
}
],
"conference": "Not Listed",
"year": "1991",
"title": "USA TODAY Diversity Index",
"description": "The USA TODAY Diversity Index was invented by Philip Meyer of the University of North Carolina and Shawn McIntosh of USA TODAY in 1991.",
"keywords": [
"diversity index",
"USA TODAY",
"Philip Meyer",
"Shawn McIntosh",
"University of North Carolina"
]
}
