  {
"id": 4983,
"authors": [
{
"name": "Martin Shelton",
"email": "mshelton@slashdot.org",
"affiliation": "Slashdot"
},
{
"name": "Matthew Mitchell",
"email": "geminiimatt@gmail.com",
"affiliation": "Gemini IMA"
},
{
"name": "Mike Tigas",
"email": "mtigas@protonmail.ch",
"affiliation": "ProtonMail"
},
{
"name": "Sequoia McDowell",
"email": "sequoia.mcdowell@gmail.com",
"affiliation": "Independent"
}
],
"conference": "Not Listed",
"year": "Not Listed",
"title": "Introduction to Digital Security for Journalists",
"description": "A guide for journalists to learn about digital security and protect themselves from cyber threats.",
"keywords": [
"digital security",
"journalism",
"cybersecurity",
"threats",
"protection"
]
}
