  {
"id": 4988,
"authors": [
{
"name": "Lynda Cohen",
"email": null,
"affiliation": "BreakingAC.com"
}
],
"conference": "Not Listed",
"year": "Not Listed",
"title": "Using Social Media and Internet in Reporting",
"description": "Lynda Cohen discusses how social media can be used to find story ideas, cull sources, and earn readers' trust. She emphasizes the importance of interacting with potential sources and building online relationships/partnerships.",
"keywords": [
"social media",
"reporting",
"sources",
"interaction",
"relationships"
]
}
