  {
"id": 5020,
"authors": [
{
"name": "Jennifer Forsyth",
"email": "jennifer.forsyth@wsj.com",
"affiliation": "Wall Street Journal"
},
{
"name": "Holly Hacker",
"email": "hhacker@dallasnews.com",
"affiliation": "Dallas News"
},
{
"name": "Andrea Fuller",
"email": "andrea.fuller@wsj.com",
"affiliation": "Wall Street Journal"
}
],
"conference": "IRE",
"year": "2015",
"title": "The Perils, Pitfalls and Payoffs of Working with Higher Ed Data",
"description": "An overview of the benefits and challenges of using higher education data, including the College Scorecard and IPEDS.",
"keywords": [
"higher education data",
"College Scorecard",
"IPEDS",
"data analysis"
]
}
