  {
"id": 5099,
"authors": [
{
"name": "Tracy Greer",
"email": null,
"affiliation": "CAR Conference"
},
{
"name": "Jennifer LaFleur",
"email": null,
"affiliation": "CAR Conference"
},
{
"name": "Jeremy Merrill",
"email": null,
"affiliation": "CAR Conference"
},
{
"name": "Katarina Sabados",
"email": null,
"affiliation": "CAR Conference"
}
],
"conference": "CAR Conference",
"year": 2017,
"title": "Getting Data Into Microsoft Access",
"description": "Learn how to import data into Microsoft Access and create tables from scratch.",
"keywords": ["Microsoft Access", "database management", "import data", "create tables"]
}
