  {
"id": 5246,
"authors": [
{
"name": "Eric Eyre",
"email": null,
"affiliation": "Charleston Gazette-Mail"
},
{
"name": "Jay Root",
"email": null,
"affiliation": "The Texas Tribune"
},
{
"name": "Barbara Rodriguez",
"email": null,
"affiliation": "The Associated Press"
}
],
"conference": "Not Listed",
"year": "Not Listed",
"title": "COVERING STATE GOVERNMENT",
"description": "Tips and strategies for reporting on state government, including how to track state contracts, purchase orders, and employee payroll forms, and how to use the phone and email effectively.",
"keywords": [
"state government",
"reporting",
"contracts",
"purchase orders",
"employee payroll forms"
]
}
