  {
"id": 5733,
"authors": [
{
"name": "Gary Harki",
"email": "gary.harki@pilotonline.com",
"affiliation": "The Virginian-Pilot"
},
{
"name": "Meg Kissinger",
"email": "meg.kissinger@jrn.com",
"affiliation": "Milwaukee Journal Sentinel"
},
{
"name": "Jessica Priest",
"email": "jpriest@vicad.com",
"affiliation": "Victoria Advocate"
}
],
"conference": "IRE",
"year": 2018,
"title": "Mental Illness and Jails",
"description": "Tips and resources for investigating the treatment of people with mental illness in the criminal justice system.",
"keywords": ["mental illness", "criminal justice", "jails", "treatment", "stigma"]
}
