  {
"id": "T1965",
"authors": [
{
"name": "Pat Stith",
"affiliation": "The News & Observer"
},
{
"name": "Better Watchdog Workshop-Tampa",
"affiliation": "Not Listed"
}
],
"conference": "Not Listed",
"year": "Not Listed",
"title": "Backgrounding Individuals",
"description": "This text provides suggestions for backgrounding individuals, including searching public records, examining driving records, and looking up information in various directories, databases, and yearbooks.",
"keywords": [
"background checks",
"public records",
"private investigation",
"journalism",
"research"
]
}
