  {
"id": "T2637",
"authors": [
{
"name": "Margot Williams",
"email": "margotwill@nytimes.com",
"affiliation": "The New York Times"
},
{
"name": "Nora Paul",
"email": "npaul@umn.edu",
"affiliation": "University of Minnesota"
}
],
"conference": "Not Listed",
"year": "Not Listed",
"title": "Advanced Internet: Google Tricks, Deep Web, and Resurrecting the Dead",
"description": "A presentation on advanced internet research techniques, including Google tricks and searching the deep web, as well as finding disappeared content and resurrecting the dead.",
"keywords": [
"Google tricks",
"deep web",
"disappeared content",
"resurrecting the dead",
"internet research"
]
}
